epyt_control/VERSION
epyt_control/__init__.py
epyt_control/controllers/__init__.py
epyt_control/controllers/lqr.py
epyt_control/controllers/pid.py
epyt_control/controllers/utils.py
epyt_control/envs/__init__.py
epyt_control/envs/advanced_quality_control_env.py
epyt_control/envs/hydraulic_control_env.py
epyt_control/envs/rl_env.py
epyt_control/envs/actions/__init__.py
epyt_control/envs/actions/actions.py
epyt_control/envs/actions/actuator_state_actions.py
epyt_control/envs/actions/pump_speed_actions.py
epyt_control/envs/actions/quality_actions.py
epyt_control/evaluation/__init__.py
epyt_control/evaluation/evaluation.py
epyt_control/evaluation/metrics.py
epyt_control/signal_processing/__init__.py
epyt_control/signal_processing/event_detection/__init__.py
epyt_control/signal_processing/event_detection/event_detector.py
epyt_control/signal_processing/event_detection/sensor_interpolation_detector.py
epyt_control/signal_processing/state_estimation/__init__.py
epyt_control/signal_processing/state_estimation/kalman_filters.py
epyt_control/signal_processing/state_estimation/smoothers.py
epyt_control/signal_processing/state_forecasting/__init__.py
epyt_control/signal_processing/state_forecasting/mlp_surrogate.py
epyt_control/signal_processing/state_forecasting/surrogates.py
epyt_control-0.5.0.dist-info/licenses/LICENSE
epyt_control-0.5.0.dist-info/METADATA
epyt_control-0.5.0.dist-info/WHEEL
epyt_control-0.5.0.dist-info/top_level.txt
epyt_control-0.5.0.dist-info/RECORD
