Metadata-Version: 2.4
Name: epyt-control
Version: 0.5.0
Summary: EPyT-Control -- EPANET Python Toolkit - Control
Author-email: André Artelt <aartelt@techfak.uni-bielefeld.de>
License-Expression: MIT
Project-URL: Homepage, https://github.com/WaterFutures/EPyT-Control
Project-URL: Documentation, https://epyt-control.readthedocs.io/en/stable/
Project-URL: Repository, https://github.com/WaterFutures/EPyT-Control.git
Project-URL: Issues, https://github.com/WaterFutures/EPyT-Control/issues
Keywords: epanet,water,networks,hydraulics,quality,simulations,control,reinforcement learning
Classifier: Development Status :: 4 - Beta
Classifier: Intended Audience :: Science/Research
Classifier: Programming Language :: Python :: 3
Classifier: Programming Language :: Python :: 3.9
Classifier: Programming Language :: Python :: 3.10
Classifier: Programming Language :: Python :: 3.11
Classifier: Programming Language :: Python :: 3.12
Classifier: Programming Language :: Python :: 3.13
Classifier: Programming Language :: Python :: 3.14
Requires-Python: >=3.9
License-File: LICENSE
Requires-Dist: epyt_flow>=0.15.0
Requires-Dist: scikit-learn>=1.4.0
Requires-Dist: stable-baselines3
Dynamic: license-file
